{"AQZKHkKyfD0cyftPor9xuQ==":"o8d%20class%20%E8%9D%B8%E7%89%9B%E5%B7%B7%E6%85%A2%E5%AD%B8%E5%A0%82-1-2000x1358.png","CVj2l6iJaaorT8tI8Nw8pA==":"o8d%20class%20%E8%9D%B8%E7%89%9B%E5%B7%B7%E6%85%A2%E5%AD%B8%E5%A0%82-1-2000x1358.png","aDrSanCK3wueDYJJ2QtYZw==":"o8d%20class%20%E8%9D%B8%E7%89%9B%E5%B7%B7%E6%85%A2%E5%AD%B8%E5%A0%82-7-122x121.png","CU49vfQccFCwuPTo0jMilA==":"o8d%20class%20%E8%9D%B8%E7%89%9B%E5%B7%B7%E6%85%A2%E5%AD%B8%E5%A0%82-1-2000x1358.png","EN5NeNjlD2dRnK1pXo1Oew==":"o8d%20class%20%E8%9D%B8%E7%89%9B%E5%B7%B7%E6%85%A2%E5%8B%95%E4%BD%9C-1-2000x1358.png","HtwojXmHhkVbzLbrXJI0UA==":"o8d%20class%20%E8%9D%B8%E7%89%9B%E5%B7%B7%E6%85%A2%E5%8B%95%E4%BD%9C-12-2000x1358.png","vOvVtnuXN7EU8rcRmoRGww==":"o8d%20class%20%E8%9D%B8%E7%89%9B%E5%B7%B7%E6%85%A2%E5%8B%95%E4%BD%9C-8-2000x1358.png","r6bjgCodtBJN3Jmz+xpFjA==":"o8d%20class%20%E8%9D%B8%E7%89%9B%E5%B7%B7%E6%85%A2%E5%8B%95%E4%BD%9C-13-2000x1358.png","0wfdiDcnUQkGcWL1kuya/g==":"o8d%20class%20%E8%9D%B8%E7%89%9B%E5%B7%B7%E6%85%A2%E5%8B%95%E4%BD%9C-11-122x121.png","SgjEzYCMsl6CySTmJr+/gA==":"o8d%20class%20%E8%9D%B8%E7%89%9B%E5%B7%B7%E6%85%A2%E5%8B%95%E4%BD%9C-13-2000x1358.png","uRKPWdtoF+hElrYr1jy++A==":"o8d%20class%20%E8%9D%B8%E7%89%9B%E5%B7%B7%E6%85%A2%E5%AD%B82%E5%A0%82-10-122x121.png","q641rH9S4Gori7UkBdsPOw==":"o8d%20class%20%E8%9D%B8%E7%89%9B%E5%B7%B7%E6%85%A2%E5%8B%95%E4%BD%9C-13-2000x1358.png"}